adapters/__init__.py
adapters/adapters.py
adapters/base.py
adapters/fields.py
adapters/helpers.py
adapters/meta.py
adapters/utils.py
python_adapters-2.1.0.dist-info/DESCRIPTION.rst
python_adapters-2.1.0.dist-info/METADATA
python_adapters-2.1.0.dist-info/RECORD
python_adapters-2.1.0.dist-info/WHEEL
python_adapters-2.1.0.dist-info/metadata.json
python_adapters-2.1.0.dist-info/top_level.txt
