Metadata-Version: 2.0
Name: python-adapters
Version: 2.1.0
Summary: Python adapters
Home-page: https://github.com/alexei/python-adapters
Author: Alexei
Author-email: hello@alexei.ro
License: UNKNOWN
Download-URL: https://github.com/alexei/python-adapters/archive/2.1.0.tar.gz
Keywords: adapter pattern
Platform: UNKNOWN
Requires-Dist: future
Requires-Dist: python-dateutil (>=2.6.0)
Requires-Dist: six
